{
  "data": {
    "list": [{
      "userName": "脐橙521",
      "userPicUrl": "https://img.meituan.net/avatar/625d111acec857671ed727cd16615c9317786.jpg",
      "userID": 697597473,
      "commentTime": "2019-11-19",
      "score": 5,
      "deliveryTime": "43分钟送达",
      "content": "只拍了一张照片，鸡块真的超nice，这个价格真的神仙!生菜说给我多一点，好像真的多了一点，但是生菜都是软趴趴那种了没有存在感。送的很及时，也很脆，很香。",
      "praiseDish": "香辣鸡腿堡+黑椒鸡块+可乐",
      "label": "",
      "pictures": [{
        "originalPicUrl": "http://p0.meituan.net/wmcomment/04da22748ca9c687693fd1e46aedfee026664.jpg",
        "smallPicUrl": "http://p0.meituan.net/wmcomment/04da22748ca9c687693fd1e46aedfee026664.jpg@160w_160h_1e_1c",
        "bigPicUrl": "http://p0.meituan.net/wmcomment/04da22748ca9c687693fd1e46aedfee026664.jpg@330w_330h_1e_1c"
      }],
      "isAnonymous": 0
    }, {
      "userName": "脐橙521",
      "userPicUrl": "https://img.meituan.net/avatar/625d111acec857671ed727cd16615c9317786.jpg",
      "userID": 697597473,
      "commentTime": "2019-10-22",
      "score": 5,
      "deliveryTime": "41分钟送达",
      "content": "生菜真的少，其他的很优秀，套餐很棒很便宜。",
      "praiseDish": "香辣鸡腿堡+地瓜丸+可乐",
      "label": "",
      "pictures": [{
        "originalPicUrl": "http://p0.meituan.net/wmcomment/ae0e47c613ed30d76a5340a451661fbe35828.jpg",
        "smallPicUrl": "http://p0.meituan.net/wmcomment/ae0e47c613ed30d76a5340a451661fbe35828.jpg@160w_160h_1e_1c",
        "bigPicUrl": "http://p0.meituan.net/wmcomment/ae0e47c613ed30d76a5340a451661fbe35828.jpg@330w_330h_1e_1c"
      }],
      "isAnonymous": 0
    }, {
      "userName": "匿名用户",
      "userPicUrl": "",
      "userID": 0,
      "commentTime": "2019-11-23",
      "score": 5,
      "deliveryTime": "30分钟送达",
      "content": "挺好吃。下次再买呀",
      "praiseDish": "单人套餐:香辣鸡腿堡+骨肉相连+可乐",
      "label": "",
      "pictures": [],
      "isAnonymous": 1
    }, {
      "userName": "HaC354773987",
      "userPicUrl": "",
      "userID": 1059058454,
      "commentTime": "2019-09-28",
      "score": 5,
      "deliveryTime": "44分钟送达",
      "content": "他家的炸鸡我跟男朋友都爱吃\uD83D\uDC44，干净，送的快，好吃。",
      "praiseDish": "",
      "label": "礼貌热情,快速准时,仪表整洁,货品完好,风雨无阻",
      "pictures": [{
        "originalPicUrl": "http://p0.meituan.net/wmcomment/448681894aa5a49cf8fde579a7ab7ff128469.jpg",
        "smallPicUrl": "http://p0.meituan.net/wmcomment/448681894aa5a49cf8fde579a7ab7ff128469.jpg@160w_160h_1e_1c",
        "bigPicUrl": "http://p0.meituan.net/wmcomment/448681894aa5a49cf8fde579a7ab7ff128469.jpg@330w_330h_1e_1c"
      }, {
        "originalPicUrl": "http://p0.meituan.net/wmcomment/67df43a09f12daed7c01b5a88200b20643915.jpg",
        "smallPicUrl": "http://p0.meituan.net/wmcomment/67df43a09f12daed7c01b5a88200b20643915.jpg@160w_160h_1e_1c",
        "bigPicUrl": "http://p0.meituan.net/wmcomment/67df43a09f12daed7c01b5a88200b20643915.jpg@330w_330h_1e_1c"
      }],
      "isAnonymous": 0
    }, {
      "userName": "apf655461659",
      "userPicUrl": "https://img.meituan.net/avatar/3099a66a212d71ef6bf976ad999ac59311552.jpg",
      "userID": 872261629,
      "commentTime": "2019-11-10",
      "score": 5,
      "deliveryTime": "38分钟送达",
      "content": "emmmm为啥没有菜 汉堡\uD83C\uDF54没有菜很难受",
      "praiseDish": "",
      "label": "礼貌热情",
      "pictures": [],
      "isAnonymous": 0
    }, {
      "userName": "晓晓61542",
      "userPicUrl": "",
      "userID": 2623414802,
      "commentTime": "2019-11-08",
      "score": 3,
      "deliveryTime": "38分钟送达",
      "content": "好好好好好好好好好好",
      "praiseDish": "脆皮全鸡",
      "label": "",
      "pictures": [],
      "isAnonymous": 0
    }, {
      "userName": "匿名用户",
      "userPicUrl": "",
      "userID": 0,
      "commentTime": "2019-11-02",
      "score": 5,
      "deliveryTime": "40分钟送达",
      "content": "味道赞，送餐快，好好吃。",
      "praiseDish": "",
      "label": "礼貌热情,货品完好,快速准时",
      "pictures": [{
        "originalPicUrl": "http://p0.meituan.net/wmcomment/364bf52f17a5f8db29ac390b6543fe7a44223.jpg",
        "smallPicUrl": "http://p0.meituan.net/wmcomment/364bf52f17a5f8db29ac390b6543fe7a44223.jpg@160w_160h_1e_1c",
        "bigPicUrl": "http://p0.meituan.net/wmcomment/364bf52f17a5f8db29ac390b6543fe7a44223.jpg@330w_330h_1e_1c"
      }],
      "isAnonymous": 1
    }, {
      "userName": "LINEN凌",
      "userPicUrl": "https://img.meituan.net/avatar/7fd21d2e36a9614c013a2a518c1c9fe49677.jpg",
      "userID": 258611207,
      "commentTime": "2019-11-04",
      "score": 5,
      "deliveryTime": "38分钟送达",
      "content": "还行吧，可以试试",
      "praiseDish": "",
      "label": "",
      "pictures": [],
      "isAnonymous": 0
    }, {
      "userName": "匿名用户",
      "userPicUrl": "",
      "userID": 0,
      "commentTime": "2019-09-21",
      "score": 5,
      "deliveryTime": "34分钟送达",
      "content": "#蜜汁手扒鸡+薯条+可乐#送少了薯条，希望下次能注意点",
      "praiseDish": "",
      "label": "",
      "pictures": [],
      "isAnonymous": 1
    }, {
      "userName": "OVb606816343",
      "userPicUrl": "https://img.meituan.net/avatar/374392e1a932adad3ab6c49bd41c94cb14128.jpg",
      "userID": 864104689,
      "commentTime": "2019-09-06",
      "score": 5,
      "deliveryTime": "41分钟送达",
      "content": "我们宿舍一直都是点这家，好吃，送得又快，还是热乎乎的",
      "praiseDish": "香辣鸡腿堡+墨西哥鸡肉卷+可乐",
      "label": "礼貌热情,快速准时,货品完好",
      "pictures": [{
        "originalPicUrl": "http://p0.meituan.net/wmcomment/5744452ee491d06d4bea7edba9f2d52d32973.jpg",
        "smallPicUrl": "http://p0.meituan.net/wmcomment/5744452ee491d06d4bea7edba9f2d52d32973.jpg@160w_160h_1e_1c",
        "bigPicUrl": "http://p0.meituan.net/wmcomment/5744452ee491d06d4bea7edba9f2d52d32973.jpg@330w_330h_1e_1c"
      }],
      "isAnonymous": 0
    }, {
      "userName": "匿名用户",
      "userPicUrl": "",
      "userID": 0,
      "commentTime": "2019-11-27",
      "score": 1,
      "deliveryTime": "26分钟送达",
      "content": "#蜜汁手扒鸡+可乐# #墨西哥鸡肉卷+骨肉相连+可乐#一点都不好，，",
      "praiseDish": "",
      "label": "少餐/洒餐",
      "pictures": [{
        "originalPicUrl": "http://p0.meituan.net/wmcomment/98d14040d25f4050cf1b6d15474ff3729228.jpg",
        "smallPicUrl": "http://p0.meituan.net/wmcomment/98d14040d25f4050cf1b6d15474ff3729228.jpg@160w_160h_1e_1c",
        "bigPicUrl": "http://p0.meituan.net/wmcomment/98d14040d25f4050cf1b6d15474ff3729228.jpg@330w_330h_1e_1c"
      }],
      "isAnonymous": 1
    }, {
      "userName": "匿名用户",
      "userPicUrl": "",
      "userID": 0,
      "commentTime": "2019-10-20",
      "score": 1,
      "deliveryTime": "24分钟送达",
      "content": "这是汉堡吗，肉夹馍差不多吧",
      "praiseDish": "",
      "label": "",
      "pictures": [{
        "originalPicUrl": "http://p0.meituan.net/wmcomment/9c108616efbc2ef580c884c2b80a573e30455.jpg",
        "smallPicUrl": "http://p0.meituan.net/wmcomment/9c108616efbc2ef580c884c2b80a573e30455.jpg@160w_160h_1e_1c",
        "bigPicUrl": "http://p0.meituan.net/wmcomment/9c108616efbc2ef580c884c2b80a573e30455.jpg@330w_330h_1e_1c"
      }],
      "isAnonymous": 1
    }, {
      "userName": "匿名用户",
      "userPicUrl": "",
      "userID": 0,
      "commentTime": "2019-11-12",
      "score": 2,
      "deliveryTime": "39分钟送达",
      "content": "可乐撒了，没给手套，盐巴什么的都没有(●.●)",
      "praiseDish": "",
      "label": "",
      "pictures": [],
      "isAnonymous": 1
    }, {
      "userName": "你家多妹妹",
      "userPicUrl": "",
      "userID": 226894783,
      "commentTime": "2019-10-26",
      "score": 3,
      "deliveryTime": "38分钟送达",
      "content": "你家这不叫汉堡 叫做面包夹肉而已",
      "praiseDish": "",
      "label": "",
      "pictures": [],
      "isAnonymous": 0
    }, {
      "userName": "匿名用户",
      "userPicUrl": "",
      "userID": 0,
      "commentTime": "2019-09-29",
      "score": 3,
      "deliveryTime": "41分钟送达",
      "content": "味道不错，希望下次看一下备注",
      "praiseDish": "",
      "label": "",
      "pictures": [],
      "isAnonymous": 1
    }, {
      "userName": "吳邪大大",
      "userPicUrl": "https://img.meituan.net/avatar/2e6fed66caa76ab29cee690b9e4be7a915223.jpg",
      "userID": 884793704,
      "commentTime": "2019-09-26",
      "score": 5,
      "deliveryTime": "21分钟送达",
      "content": "可乐居然忘记给我去冰了。",
      "praiseDish": "2个香辣鸡腿堡+可乐",
      "label": "",
      "pictures": [],
      "isAnonymous": 0
    }, {
      "userName": "oSx362835045",
      "userPicUrl": "",
      "userID": 1477525467,
      "commentTime": "2019-09-25",
      "score": 5,
      "deliveryTime": "17分钟送达",
      "content": "配送非常快，食物也不错",
      "praiseDish": "",
      "label": "",
      "pictures": [],
      "isAnonymous": 0
    }, {
      "userName": "吳邪大大",
      "userPicUrl": "https://img.meituan.net/avatar/2e6fed66caa76ab29cee690b9e4be7a915223.jpg",
      "userID": 884793704,
      "commentTime": "2019-09-17",
      "score": 5,
      "deliveryTime": "14分钟送达",
      "content": "就只给了我一张餐巾纸。",
      "praiseDish": "",
      "label": "",
      "pictures": [],
      "isAnonymous": 0
    }, {
      "userName": "MarmotAC973",
      "userPicUrl": "",
      "userID": 2573706052,
      "commentTime": "2019-07-08",
      "score": 3,
      "deliveryTime": "41分钟送达",
      "content": "在你们家已经点了十多餐了，鸡肉卷里裹甜面酱（还是黄豆酱）是啥操作( ꒪Д꒪)两天没点你们连菜谱都换了吗(ㅍ_ㅍ)加那玩意超难吃的好吧，黑乎乎的，又黏又腻，建议换成番茄或者沙拉酱",
      "praiseDish": "",
      "label": "",
      "pictures": [],
      "isAnonymous": 0
    }, {
      "userName": "阿永娴",
      "userPicUrl": "https://img.meituan.net/avatar/adaac2f19aad51bc6c30634e979b1079108542.jpg",
      "userID": 1712737905,
      "commentTime": "2019-08-03",
      "score": 4,
      "deliveryTime": "29分钟送达",
      "content": "味道不错超赞的 比我之前点的都要好吃得多 ",
      "praiseDish": "墨西哥鸡肉卷+炸鸡腿+可乐",
      "label": "穿戴工服,快速准时,货品完好,仪表整洁,风雨无阻,礼貌热情",
      "pictures": [],
      "isAnonymous": 0
    }],
    "recordCount": 4190,
    "startIndex": 0,
    "nextStartIndex": 20,
    "isEnd": false,
    "shopId": 1194593615,
    "mtWmPoiId": "957611397877071",
    "dpCommentNum": 0,
    "PraiseRatio": "商家好评率92%",
    "buzCode": 0,
    "qualityScore": 4.3,
    "packScore": 4.3,
    "integratedScore": 4.4,
    "shopScore": 4.4,
    "deliveryScore": 4.9,
    "commentLabels": [{
      "content": "全部(4190)",
      "type": 1,
      "isSelected": 1,
      "ID": 0
    }, {
      "content": "好评(3876)",
      "type": 1,
      "isSelected": 0,
      "ID": 1
    }, {
      "content": "差评(176)",
      "type": 1,
      "isSelected": 0,
      "ID": 3
    }, {
      "content": "有图评价(66)",
      "type": 1,
      "isSelected": 0,
      "ID": 5
    }, {
      "content": "味道赞(107)",
      "type": 2,
      "isSelected": 0,
      "ID": 75
    }, {
      "content": "价格实惠(18)",
      "type": 2,
      "isSelected": 0,
      "ID": 61
    }, {
      "content": "服务好(15)",
      "type": 2,
      "isSelected": 0,
      "ID": 39
    }, {
      "content": "满意(11)",
      "type": 2,
      "isSelected": 0,
      "ID": 34
    }, {
      "content": "分量足(5)",
      "type": 2,
      "isSelected": 0,
      "ID": 50
    }, {
      "content": "肉类不错(5)",
      "type": 2,
      "isSelected": 0,
      "ID": 4
    }]
  },
  "code": 0,
  "msg": "成功"
}